herdcalls/__init__.py
herdcalls/environment.py
herdcalls/exceptions.py
herdcalls/ffmpeg.py
herdcalls/herdcalls.py
herdcalls/herdcalls_session.py
herdcalls/mtproto_required.py
herdcalls/mutex.py
herdcalls/scaffold.py
herdcalls/statictypes.py
herdcalls/stream_type.py
herdcalls/sync.py
herdcalls/to_async.py
herdcalls/version_manager.py
herdcalls/ytdlp.py
herdcalls/custom_api/__init__.py
herdcalls/custom_api/custom_api.py
herdcalls/handlers/__init__.py
herdcalls/handlers/handlers_holder.py
herdcalls/media_devices/__init__.py
herdcalls/media_devices/device_info.py
herdcalls/media_devices/media_devices.py
herdcalls/media_devices/screen_info.py
herdcalls/methods/__init__.py
herdcalls/methods/decorators/__init__.py
herdcalls/methods/decorators/on_closed_voice_chat.py
herdcalls/methods/decorators/on_group_call_invite.py
herdcalls/methods/decorators/on_kicked.py
herdcalls/methods/decorators/on_left.py
herdcalls/methods/decorators/on_participants_change.py
herdcalls/methods/decorators/on_stream_end.py
herdcalls/methods/groups/__init__.py
herdcalls/methods/groups/change_volume_call.py
herdcalls/methods/groups/get_participants.py
herdcalls/methods/groups/join_group_call.py
herdcalls/methods/groups/leave_group_call.py
herdcalls/methods/stream/__init__.py
herdcalls/methods/stream/change_stream.py
herdcalls/methods/stream/mute_stream.py
herdcalls/methods/stream/pause_stream.py
herdcalls/methods/stream/played_time.py
herdcalls/methods/stream/resume_stream.py
herdcalls/methods/stream/unmute_stream.py
herdcalls/methods/utilities/__init__.py
herdcalls/methods/utilities/cache_peer.py
herdcalls/methods/utilities/call_holder.py
herdcalls/methods/utilities/get_max_voice_chat.py
herdcalls/methods/utilities/idle.py
herdcalls/methods/utilities/mtproto_handler.py
herdcalls/methods/utilities/ping.py
herdcalls/methods/utilities/resolve_chat_id.py
herdcalls/methods/utilities/run.py
herdcalls/methods/utilities/start.py
herdcalls/methods/utilities/stream_params.py
herdcalls/mtproto/__init__.py
herdcalls-0.1.1.dist-info/LICENSE
herdcalls-0.1.1.dist-info/METADATA
herdcalls-0.1.1.dist-info/WHEEL
herdcalls-0.1.1.dist-info/top_level.txt
herdcalls-0.1.1.dist-info/RECORD
