Metadata-Version: 2.1
Name: herdcalls
Version: 0.1.1
Home-page: https://github.com/OnTheHerd/herdcalls
Author: OnTheHerd
Author-email: oth@pyroherd.org
License: LGPL-3.0
Classifier: License :: OSI Approved :: GNU Lesser General Public License v3 (LGPLv3)
Classifier: Operating System :: OS Independent
Classifier: Programming Language :: Python :: 3
Classifier: Programming Language :: Python :: 3 :: Only
Classifier: Programming Language :: Python :: 3.8
Classifier: Programming Language :: Python :: 3.9
Classifier: Programming Language :: Python :: 3.10
Classifier: Programming Language :: Python :: 3.11
Classifier: Programming Language :: Python :: 3.12
Classifier: Programming Language :: Python :: Implementation :: CPython
Requires-Python: >=3.8
License-File: LICENSE
Requires-Dist: aiohttp >=3.9.3
Requires-Dist: ntgcalls >=1.1.2
Requires-Dist: psutil
Requires-Dist: screeninfo
Requires-Dist: deprecation
Requires-Dist: setuptools
